{"GDaQhUEWFF7XtfOf8PUvQg==":"reddit-90x90.png","rmITVhC6tz9OQ6dFvBl4gA==":"reddit-1-90x90.png","sqr5uNk9e10ohMMfRCp+1Q==":"untitled%20design-1920x1080.jpg","yiA/GofBCXP5ZDfEdQypuw==":"untitled%20design-1920x1080.jpeg","mAYkZY2LM6uk66fMpYjfsw==":"untitled%20design-1920x1080.png","hPkRNnCmTEeH+xfVrqaZ6g==":"untitled%2520design_auto_x2-2000x1124.png","6G24gDEnhk7ISGH2ykhVMg==":"unknown-720x389.png","Gn1Xi1yjve4xB73a6SbNGA==":"unknown-1-720x389.png","SKp8OKTVN+yKBF4NL/YPxg==":"unknown-2-720x389.png","IbDGbr0s5DT2PvO9djHlDA==":"unknown569-800x443.png","Sd+Mifxcv+lt4vcwUkI2sg==":"unknown-3-720x389.png","nubOlIhb/+WO8eOxwvXYvQ==":"unknown569-1-800x443.png","3bQqhTOT3nQ0gvyRjJ9tyQ==":"unknown569-2-800x443.png","BBh62RlI//Y84FK/rF0r9Q==":"unknown576-374x135.png","KuW6mUXdVdDbzltIRtSaKw==":"unknown576-1-374x135.png","O71JMwshp3UIohR81vL3Zw==":"unknown747-796x645.png","RWnyRNkzQjAIlISehAW5eg==":"unknown839-568x353.png","SmIB0E8xEtJjcXpRcC9YMw==":"unknown747-1-796x645.png","gtUaUHss1KnRuvPlrnvFIQ==":"ee7c382d9257652a88c8f7b7f22a994d-1076x565.png"}